hvrt/__init__.py
hvrt/partitioner.py
hvrt_partitioner-0.6.1.dist-info/licenses/LICENSE
metrics/__init__.py
metrics/feature_data.py
metrics/metrics.py
metrics/partition_profiler.py
hvrt_partitioner-0.6.1.dist-info/METADATA
hvrt_partitioner-0.6.1.dist-info/WHEEL
hvrt_partitioner-0.6.1.dist-info/top_level.txt
hvrt_partitioner-0.6.1.dist-info/RECORD
