Metadata-Version: 2.4
Name: hvrt-partitioner
Version: 0.6.1
Summary: A fast, scalable algorithm for creating data partitions based on a hybrid variance-reduction tree method.
Author: Jake
Project-URL: Homepage, https://github.com/HotProtato/H-VRT
Classifier: Programming Language :: Python :: 3
Classifier: Operating System :: OS Independent
Classifier: Intended Audience :: Science/Research
Classifier: Topic :: Scientific/Engineering :: Artificial Intelligence
Classifier: Topic :: Software Development :: Libraries :: Python Modules
Requires-Python: >=3.8
License-File: LICENSE
Requires-Dist: numpy
Requires-Dist: scikit-learn
Requires-Dist: pandas
Provides-Extra: test
Requires-Dist: pytest; extra == "test"
Provides-Extra: viz
Requires-Dist: matplotlib; extra == "viz"
Requires-Dist: seaborn; extra == "viz"
Dynamic: license-file
